LICENSE
MANIFEST.in
README.md
pyproject.toml
setup.cfg
setup.py
src/pypeakify/__init__.py
src/pypeakify/baseline.py
src/pypeakify/deconvolution.py
src/pypeakify/filereader.py
src/pypeakify/peak.py
src/pypeakify.egg-info/PKG-INFO
src/pypeakify.egg-info/SOURCES.txt
src/pypeakify.egg-info/dependency_links.txt
src/pypeakify.egg-info/requires.txt
src/pypeakify.egg-info/top_level.txt