Metadata-Version: 2.1
Name: pypeakify
Version: 1.0.1
Summary: General purpose peak deconvolution package for Python.
Author: mscloudlab
Author-email: mscloudlab@gmail.com
Classifier: Programming Language :: Python :: 3
Classifier: Operating System :: OS Independent
Requires-Python: >=3.6
License-File: LICENSE
